[{"controls":{"direction":0,"turn":0,"cameraRotation":0},"timeout":70},{"controls":{"direction":0,"turn":0,"cameraRotation":0},"timeout":181},{"controls":{"direction":0,"turn":0,"cameraRotation":0},"timeout":265},{"controls":{"direction":0,"turn":0,"cameraRotation":0},"timeout":370},{"controls":{"direction":0,"turn":0,"cameraRotation":0},"timeout":479},{"controls":{"direction":0,"turn":0,"cameraRotation":0},"timeout":578},{"controls":{"direction":0,"turn":0,"cameraRotation":0},"timeout":672},{"controls":{"direction":0,"turn":0,"cameraRotation":0},"timeout":768},{"controls":{"direction":0.3,"turn":0,"cameraRotation":0},"timeout":871},{"controls":{"direction":0.8,"turn":0,"cameraRotation":0},"timeout":992},{"controls":{"direction":1,"turn":0,"cameraRotation":0},"timeout":1074},{"controls":{"direction":1,"turn":0,"cameraRotation":0},"timeout":1180},{"controls":{"direction":1,"turn":0,"cameraRotation":0},"timeout":1274},{"controls":{"direction":1,"turn":0,"cameraRotation":0},"timeout":1378},{"controls":{"direction":1,"turn":0,"cameraRotation":0},"timeout":1470},{"controls":{"direction":1,"turn":0,"cameraRotation":0},"timeout":1576},{"controls":{"direction":1,"turn":0,"cameraRotation":0},"timeout":1680},{"controls":{"direction":1,"turn":0,"cameraRotation":0},"timeout":1792},{"controls":{"direction":0,"turn":0,"cameraRotation":0},"timeout":1869},{"controls":{"direction":0,"turn":0,"cameraRotation":0},"timeout":1988},{"controls":{"direction":0,"turn":"-0.1","cameraRotation":0},"timeout":2074},{"controls":{"direction":0,"turn":"-1.0","cameraRotation":0},"timeout":2176},{"controls":{"direction":0,"turn":"-0.2","cameraRotation":0},"timeout":2277},{"controls":{"direction":0,"turn":0,"cameraRotation":0},"timeout":2388},{"controls":{"direction":0,"turn":"-0.4","cameraRotation":0},"timeout":2474},{"controls":{"direction":0,"turn":0,"cameraRotation":0},"timeout":2577},{"controls":{"direction":0,"turn":0,"cameraRotation":0},"timeout":2683},{"controls":{"direction":0,"turn":0,"cameraRotation":0},"timeout":2781},{"controls":{"direction":0,"turn":0,"cameraRotation":0},"timeout":2877},{"controls":{"direction":1,"turn":0,"cameraRotation":0},"timeout":2994},{"controls":{"direction":1,"turn":0,"cameraRotation":0},"timeout":3073},{"controls":{"direction":1,"turn":0,"cameraRotation":0},"timeout":3177},{"controls":{"direction":1,"turn":0,"cameraRotation":0},"timeout":3266},{"controls":{"direction":1,"turn":0,"cameraRotation":0},"timeout":3376},{"controls":{"direction":1,"turn":0,"cameraRotation":0},"timeout":3487},{"controls":{"direction":1,"turn":0,"cameraRotation":0},"timeout":3577},{"controls":{"direction":0,"turn":0,"cameraRotation":0},"timeout":3666},{"controls":{"direction":0,"turn":0,"cameraRotation":0},"timeout":3798},{"controls":{"direction":0,"turn":"-1.0","cameraRotation":0},"timeout":3881},{"controls":{"direction":0,"turn":"-1.0","cameraRotation":0},"timeout":3969},{"controls":{"direction":0,"turn":0,"cameraRotation":0},"timeout":4078},{"controls":{"direction":0,"turn":0,"cameraRotation":0},"timeout":4167},{"controls":{"direction":0,"turn":"-0.6","cameraRotation":0},"timeout":4278},{"controls":{"direction":0,"turn":0,"cameraRotation":0},"timeout":4384},{"controls":{"direction":0,"turn":0,"cameraRotation":0},"timeout":4474},{"controls":{"direction":0,"turn":0,"cameraRotation":0},"timeout":4580},{"controls":{"direction":0,"turn":0,"cameraRotation":0},"timeout":4707},{"controls":{"direction":0,"turn":"-0.5","cameraRotation":0},"timeout":4782},{"controls":{"direction":0,"turn":0,"cameraRotation":0},"timeout":4876},{"controls":{"direction":0,"turn":0,"cameraRotation":0},"timeout":4974},{"controls":{"direction":0,"turn":0,"cameraRotation":0},"timeout":5066},{"controls":{"direction":1,"turn":0,"cameraRotation":0},"timeout":5177},{"controls":{"direction":1,"turn":0,"cameraRotation":0},"timeout":5269},{"controls":{"direction":1,"turn":0,"cameraRotation":0},"timeout":5385},{"controls":{"direction":1,"turn":0,"cameraRotation":0},"timeout":5470},{"controls":{"direction":1,"turn":0,"cameraRotation":0},"timeout":5566},{"controls":{"direction":1,"turn":0,"cameraRotation":0},"timeout":5668},{"controls":{"direction":1,"turn":0,"cameraRotation":0},"timeout":5775},{"controls":{"direction":1,"turn":0,"cameraRotation":0},"timeout":5882},{"controls":{"direction":0,"turn":0,"cameraRotation":0},"timeout":5973},{"controls":{"direction":0,"turn":0,"cameraRotation":0},"timeout":6070},{"controls":{"direction":0,"turn":"-0.2","cameraRotation":0},"timeout":6173},{"controls":{"direction":0,"turn":"-1.0","cameraRotation":0},"timeout":6271},{"controls":{"direction":0,"turn":"-0.7","cameraRotation":0},"timeout":6380},{"controls":{"direction":0,"turn":0,"cameraRotation":0},"timeout":6479},{"controls":{"direction":0,"turn":0,"cameraRotation":0},"timeout":6588},{"controls":{"direction":0,"turn":0,"cameraRotation":0},"timeout":6724},{"controls":{"direction":0,"turn":0,"cameraRotation":0},"timeout":6888},{"controls":{"direction":0.1,"turn":0,"cameraRotation":0},"timeout":6929},{"controls":{"direction":1,"turn":0,"cameraRotation":0},"timeout":7156},{"controls":{"direction":1,"turn":0,"cameraRotation":0},"timeout":7167},{"controls":{"direction":1,"turn":0,"cameraRotation":0},"timeout":7168},{"controls":{"direction":1,"turn":0,"cameraRotation":0},"timeout":7265},{"controls":{"direction":1,"turn":0,"cameraRotation":0},"timeout":7373},{"controls":{"direction":0,"turn":0,"cameraRotation":0},"timeout":7466},{"controls":{"direction":0,"turn":0,"cameraRotation":0},"timeout":7572},{"controls":{"direction":0,"turn":0,"cameraRotation":0},"timeout":7664},{"controls":{"direction":0,"turn":0,"cameraRotation":0},"timeout":7780},{"controls":{"direction":0.2,"turn":0,"cameraRotation":0},"timeout":7878},{"controls":{"direction":0,"turn":0,"cameraRotation":0},"timeout":7975},{"controls":{"direction":0,"turn":0,"cameraRotation":0},"timeout":8079},{"controls":{"direction":0,"turn":0,"cameraRotation":0},"timeout":8169},{"controls":{"direction":0,"turn":0,"cameraRotation":0},"timeout":8276},{"controls":{"direction":0,"turn":"-1.0","cameraRotation":0},"timeout":8381},{"controls":{"direction":0,"turn":0,"cameraRotation":0},"timeout":8484},{"controls":{"direction":0,"turn":0,"cameraRotation":0},"timeout":8578},{"controls":{"direction":0,"turn":0,"cameraRotation":0},"timeout":8672},{"controls":{"direction":0,"turn":"-0.1","cameraRotation":0},"timeout":8776},{"controls":{"direction":0,"turn":"-0.9","cameraRotation":0},"timeout":8878},{"controls":{"direction":0,"turn":0,"cameraRotation":0},"timeout":8996},{"controls":{"direction":0,"turn":0,"cameraRotation":0},"timeout":9084},{"controls":{"direction":0.1,"turn":0,"cameraRotation":0},"timeout":9166},{"controls":{"direction":0.5,"turn":0,"cameraRotation":0},"timeout":9269},{"controls":{"direction":0,"turn":0,"cameraRotation":0},"timeout":9374},{"controls":{"direction":0,"turn":0,"cameraRotation":0},"timeout":9483},{"controls":{"direction":0,"turn":"-0.9","cameraRotation":0},"timeout":9574},{"controls":{"direction":0,"turn":0,"cameraRotation":0},"timeout":9667},{"controls":{"direction":0,"turn":0,"cameraRotation":0},"timeout":9770},{"controls":{"direction":0,"turn":0,"cameraRotation":0},"timeout":9865},{"controls":{"direction":0,"turn":"-0.3","cameraRotation":0},"timeout":9967},{"controls":{"direction":0,"turn":"-0.4","cameraRotation":0},"timeout":10072},{"controls":{"direction":0,"turn":0,"cameraRotation":0},"timeout":10170},{"controls":{"direction":0,"turn":0,"cameraRotation":0},"timeout":10282},{"controls":{"direction":0,"turn":0,"cameraRotation":0},"timeout":10370},{"controls":{"direction":0,"turn":0,"cameraRotation":0},"timeout":10477},{"controls":{"direction":0,"turn":0,"cameraRotation":0},"timeout":10575},{"controls":{"direction":0,"turn":"0.5","cameraRotation":0},"timeout":10677},{"controls":{"direction":0,"turn":0,"cameraRotation":0},"timeout":10777},{"controls":{"direction":0,"turn":0,"cameraRotation":0},"timeout":10867},{"controls":{"direction":0,"turn":0,"cameraRotation":0},"timeout":10983},{"controls":{"direction":0,"turn":0,"cameraRotation":0},"timeout":11067},{"controls":{"direction":0,"turn":0,"cameraRotation":0},"timeout":11167},{"controls":{"direction":0,"turn":0,"cameraRotation":0},"timeout":11288},{"controls":{"direction":0,"turn":0,"cameraRotation":0},"timeout":11374},{"controls":{"direction":0,"turn":0,"cameraRotation":0},"timeout":11474},{"controls":{"direction":0,"turn":0,"cameraRotation":0},"timeout":11578},{"controls":{"direction":0,"turn":0,"cameraRotation":0},"timeout":11674},{"controls":{"direction":0,"turn":0,"cameraRotation":0},"timeout":11771},{"controls":{"direction":0,"turn":0,"cameraRotation":0},"timeout":11881},{"controls":{"direction":0,"turn":0,"cameraRotation":0},"timeout":11987},{"controls":{"direction":0,"turn":0,"cameraRotation":0},"timeout":12069},{"controls":{"direction":0,"turn":0,"cameraRotation":0},"timeout":12178},{"controls":{"direction":0,"turn":0,"cameraRotation":0},"timeout":12285}]